identinum/__about__.py
identinum/__init__.py
identinum/cli.py
identinum/main.py
identinum-0.7.1.dist-info/LICENSE.txt
identinum-0.7.1.dist-info/METADATA
identinum-0.7.1.dist-info/WHEEL
identinum-0.7.1.dist-info/entry_points.txt
identinum-0.7.1.dist-info/top_level.txt
identinum-0.7.1.dist-info/RECORD
