Metadata-Version: 2.1
Name: identinum
Version: 0.7.1
Summary: Guess symbolic expressions from decimals
Author-email: Nico Schlömer <nico.schloemer@gmail.com>
License: The MIT License (MIT)
Project-URL: Homepage, https://github.com/nschloe/identinum
Project-URL: Issues, https://github.com/nschloe/identinum/issues
Project-URL: Funding, https://github.com/sponsors/nschloe
Classifier: Development Status :: 5 - Production/Stable
Classifier: Intended Audience :: Science/Research
Classifier: License :: OSI Approved :: MIT License
Classifier: Operating System :: OS Independent
Classifier: Programming Language :: Python
Classifier: Programming Language :: Python :: 3
Classifier: Programming Language :: Python :: 3.7
Classifier: Programming Language :: Python :: 3.8
Classifier: Programming Language :: Python :: 3.9
Classifier: Programming Language :: Python :: 3.10
Classifier: Programming Language :: Python :: 3.11
Classifier: Topic :: Scientific/Engineering
Classifier: Topic :: Utilities
Requires-Python: >=3.7
License-File: LICENSE.txt
Requires-Dist: mpmath
Requires-Dist: sympy
